qPython_nocython-2.0.0.data/data/CHANGELOG.txt
qPython_nocython-2.0.0.data/data/LICENSE
qPython_nocython-2.0.0.data/data/README.rst
qPython_nocython-2.0.0.data/data/requirements.txt
qpython/__init__.py
qpython/_pandas.py
qpython/fastutils.pyx
qpython/qcollection.py
qpython/qconnection.py
qpython/qreader.py
qpython/qtemporal.py
qpython/qtype.py
qpython/qwriter.py
qpython/utils.py
qPython_nocython-2.0.0.dist-info/LICENSE
qPython_nocython-2.0.0.dist-info/METADATA
qPython_nocython-2.0.0.dist-info/WHEEL
qPython_nocython-2.0.0.dist-info/top_level.txt
qPython_nocython-2.0.0.dist-info/RECORD
